kgcl/apply/__init__.py
kgcl/apply/graph_transformer.py
kgcl/apply/kgcl_2_sparql.py
kgcl/diff/__init__.py
kgcl/diff/change_detection.py
kgcl/diff/diff_2_kgcl.py
kgcl/diff/diff_2_kgcl_existential.py
kgcl/diff/diff_2_kgcl_single.py
kgcl/diff/diff_2_kgcl_triple_annotation.py
kgcl/diff/graph_diff.py
kgcl/diff/owlstar_sublanguage.py
kgcl/diff/pretty_print_kgcl.py
kgcl/diff/render_operations.py
kgcl/diff/summary_generation.py
kgcl/grammar/__init__.py
kgcl/grammar/kgcl.lark
kgcl/grammar/parser.py
kgcl/model/__init__.py
kgcl/model/basics.py
kgcl/model/kgcl.py
kgcl/model/ontology_model.py
kgcl/model/prov.py
kgcl-0.0.10.dist-info/LICENSE
kgcl-0.0.10.dist-info/METADATA
kgcl-0.0.10.dist-info/WHEEL
kgcl-0.0.10.dist-info/top_level.txt
kgcl-0.0.10.dist-info/RECORD
