Metadata-Version: 2.1
Name: kgcl
Version: 0.0.10
Summary: Knowledge Graph Change Language
Home-page: https://github.com/ckindermann/knowledge-graph-change-language
Author: Christian Kindermann
Author-email: chris.kind.man@gmail.com
License: UNKNOWN
Platform: UNKNOWN
Classifier: Programming Language :: Python :: 3.8
License-File: LICENSE
Requires-Dist: linkml (~=1.0.3)
Requires-Dist: lark (~=0.11.3)
Provides-Extra: dev
Requires-Dist: pytest (>=3.7) ; extra == 'dev'
